GGST/__init__.py
GGST/API.py
GGST/constants.py
ggst_api-0.0.3.dist-info/WHEEL
ggst_api-0.0.3.dist-info/METADATA
ggst_api-0.0.3.dist-info/RECORD
