Metadata-Version: 2.1
Name: ggst-api
Version: 0.0.3
Summary: Guilty Gear Strive API wrapper
Author: UnknownMemory
Author-email: jeremyschneider21@gmail.com
Requires-Python: >=3.9,<4.0
Classifier: Programming Language :: Python :: 3
Classifier: Programming Language :: Python :: 3.10
Classifier: Programming Language :: Python :: 3.9
Requires-Dist: msgpack (>=1.0.3,<2.0.0)
Requires-Dist: python-dotenv (>=0.20.0,<0.21.0)
Requires-Dist: requests (>=2.27.1,<3.0.0)
